QuantKit/Portfolio.py
QuantKit/__init__.py
QuantKit/data_fetching.py
QuantKit/indicators.py
QuantKit/risk.py
QuantKit/visualization.py
Stockify/Portfolio.py
Stockify/__init__.py
Stockify/data_fetching.py
Stockify/indicators.py
Stockify/risk.py
Stockify/visualization.py
Stockify-0.1.2.dist-info/LICENSE
Stockify-0.1.2.dist-info/METADATA
Stockify-0.1.2.dist-info/WHEEL
Stockify-0.1.2.dist-info/top_level.txt
Stockify-0.1.2.dist-info/RECORD
