Metadata-Version: 2.1
Name: Stockify
Version: 0.1.2
Summary: A Python library for financial data analysis and portfolio management
Home-page: https://github.com/ray-singh/Stockify
Author: Rayansh Singh
Author-email: rayansh365@gmail.com
Classifier: Programming Language :: Python :: 3
Classifier: License :: OSI Approved :: MIT License
Classifier: Operating System :: OS Independent
Requires-Python: >=3.7
License-File: LICENSE
Requires-Dist: yfinance
Requires-Dist: numpy
Requires-Dist: pandas
Requires-Dist: matplotlib
Requires-Dist: scipy
Requires-Dist: datetime
Requires-Dist: seaborn
